mork/__init__.py
mork/auth.py
mork/conf.py
mork/db.py
mork/exceptions.py
mork/mail.py
mork/utils.py
mork/api/__init__.py
mork/api/health.py
mork/api/v1/__init__.py
mork/api/v1/routers/__init__.py
mork/api/v1/routers/tasks.py
mork/api/v1/routers/users.py
mork/celery/__init__.py
mork/celery/celery_app.py
mork/celery/probe.py
mork/celery/utils.py
mork/celery/tasks/__init__.py
mork/celery/tasks/deletion.py
mork/celery/tasks/edx.py
mork/celery/tasks/emailing.py
mork/celery/tasks/sarbacane.py
mork/edx/__init__.py
mork/edx/mongo/__init__.py
mork/edx/mongo/crud.py
mork/edx/mongo/database.py
mork/edx/mongo/factories.py
mork/edx/mongo/models.py
mork/edx/mysql/__init__.py
mork/edx/mysql/crud.py
mork/edx/mysql/database.py
mork/edx/mysql/factories/__init__.py
mork/edx/mysql/factories/auth.py
mork/edx/mysql/factories/base.py
mork/edx/mysql/factories/bulk.py
mork/edx/mysql/factories/certificates.py
mork/edx/mysql/factories/contentstore.py
mork/edx/mysql/factories/course.py
mork/edx/mysql/factories/courseware.py
mork/edx/mysql/factories/dark.py
mork/edx/mysql/factories/django.py
mork/edx/mysql/factories/instructor.py
mork/edx/mysql/factories/notify.py
mork/edx/mysql/factories/payment.py
mork/edx/mysql/factories/proctoru.py
mork/edx/mysql/factories/student.py
mork/edx/mysql/factories/user.py
mork/edx/mysql/factories/util.py
mork/edx/mysql/factories/verify.py
mork/edx/mysql/factories/wiki.py
mork/edx/mysql/models/__init__.py
mork/edx/mysql/models/auth.py
mork/edx/mysql/models/base.py
mork/edx/mysql/models/bulk.py
mork/edx/mysql/models/certificates.py
mork/edx/mysql/models/contentstore.py
mork/edx/mysql/models/course.py
mork/edx/mysql/models/courseware.py
mork/edx/mysql/models/dark.py
mork/edx/mysql/models/django.py
mork/edx/mysql/models/instructor.py
mork/edx/mysql/models/notify.py
mork/edx/mysql/models/payment.py
mork/edx/mysql/models/proctoru.py
mork/edx/mysql/models/student.py
mork/edx/mysql/models/user.py
mork/edx/mysql/models/util.py
mork/edx/mysql/models/verify.py
mork_ork-0.11.0.dist-info/METADATA
mork_ork-0.11.0.dist-info/WHEEL
mork_ork-0.11.0.dist-info/top_level.txt
mork_ork-0.11.0.dist-info/RECORD
